pyap/__init__.py
pyap/pyap.py
yap_tool/__init__.py
yap_tool/yap_tool.py
pyap_tdk-0.0.6.dist-info/LICENSE
pyap_tdk-0.0.6.dist-info/METADATA
pyap_tdk-0.0.6.dist-info/WHEEL
pyap_tdk-0.0.6.dist-info/top_level.txt
pyap_tdk-0.0.6.dist-info/RECORD
