Metadata-Version: 2.1
Name: pyap-tdk
Version: 0.0.6
Summary: A package to integrate with the Yap tool
Home-page: https://github.com/TechnionTDK/pyap
Author: TDK
Author-email: author@example.com
License: UNKNOWN
Platform: UNKNOWN
Classifier: Programming Language :: Python :: 3
Classifier: License :: OSI Approved :: MIT License
Classifier: Operating System :: OS Independent
Requires-Python: >=3.6
